amarket/__init__.py
amarket/asset_set.py
amarket/position.py
amarket/symbol_account_mixin.py
amarket/symbol_mixin.py
amarket-0.1.0.dist-info/METADATA
amarket-0.1.0.dist-info/WHEEL
amarket-0.1.0.dist-info/top_level.txt
amarket-0.1.0.dist-info/RECORD
