Metadata-Version: 2.4
Name: amarket
Version: 0.1.0
Author-email: Andrey Andreev <andyceo@yandex.ru>
Project-URL: Homepage, https://github.com/andyceo/amarket
Project-URL: Issues, https://github.com/andyceo/amarket/issues
Classifier: Programming Language :: Python :: 3
Classifier: Operating System :: OS Independent
Requires-Python: >=3.11
